reel/__init__.py
reel/_daemon.py
reel/_reel.py
reel/_server.py
reel/_spool.py
reel/_streamer.py
reel/_track.py
reel/_transport.py
reel/cli.py
reel/config.py
reel/keyboard.py
reel/cmd/__init__.py
reel/cmd/_aria2.py
reel/cmd/_redis.py
reel/cmd/ffmpeg.py
reel/cmd/ffprobe.py
reel/cmd/icecast.py
reel/cmd/sox.py
reel/templates/icecast.xml
reel/templates/redis.conf
tests/__init__.py
tests/conftest.py
tests/test_api.py
tests/test_cli.py
tests/test_cmd.py
tests/test_config.py
tests/test_io.py
tests/test_keyboard.py
tests/test_proc.py
tests/test_reel.py
tests/test_spool.py
tests/test_track.py
reel-0.0.8.dist-info/LICENSE
reel-0.0.8.dist-info/METADATA
reel-0.0.8.dist-info/WHEEL
reel-0.0.8.dist-info/entry_points.txt
reel-0.0.8.dist-info/top_level.txt
reel-0.0.8.dist-info/RECORD
