Metadata-Version: 2.1
Name: reel
Version: 0.0.8
Summary: A contraption for async subprocess streaming
Home-page: http://github.com/zthompson47/reel
Author: Zach Thompson
Author-email: zach@allotropic.com
License: MIT
Platform: UNKNOWN
Classifier: Programming Language :: Python :: 3.5
Classifier: License :: OSI Approved :: MIT License
Classifier: Operating System :: OS Independent
Requires-Dist: trio (>=0.10.0)
